oxford/__init__.py
oxford/wrapper.py
Oxford.py-0.0.4.dist-info/LICENSE
Oxford.py-0.0.4.dist-info/METADATA
Oxford.py-0.0.4.dist-info/WHEEL
Oxford.py-0.0.4.dist-info/top_level.txt
Oxford.py-0.0.4.dist-info/RECORD
