Metadata-Version: 2.1
Name: Oxford.py
Version: 0.0.4
Summary: Oxford API wrapper
Home-page: https://github.com/ProjectsWithPython/Oxford.py
Author: Haider Ali
Author-email: ali075398@gmail.com
License: UNKNOWN
Project-URL: Bug Tracker, https://github.com/ProjectsWithPython/Oxford.py/issues
Platform: UNKNOWN
Classifier: Programming Language :: Python :: 3
Classifier: License :: OSI Approved :: MIT License
Classifier: Operating System :: OS Independent
Requires-Python: >=3.6
License-File: LICENSE
Requires-Dist: aiohttp
